{"stats":{"minecraft:killed_by":{"minecraft:piglin_brute":3,"minecraft:zombie":3,"minecraft:wither":1,"minecraft:wither_skeleton":2,"minecraft:zombified_piglin":2,"minecraft:creeper":1,"minecraft:piglin":1,"minecraft:player":4,"minecraft:iron_golem":6,"minecraft:skeleton":2},"minecraft:broken":{"minecraft:golden_boots":1,"minecraft:diamond_helmet":1,"minecraft:diamond_pickaxe":3,"minecraft:diamond_leggings":1,"minecraft:iron_pickaxe":3,"minecraft:diamond_boots":1,"minecraft:diamond_chestplate":1},"minecraft:killed":{"minecraft:skeleton":28,"minecraft:iron_golem":3,"minecraft:pillager":21,"minecraft:zombie":46,"minecraft:cow":42,"minecraft:horse":5,"minecraft:wandering_trader":1,"minecraft:zombified_piglin":6,"minecraft:spider":10,"minecraft:silverfish":3,"minecraft:piglin_brute":1,"minecraft:piglin":15,"minecraft:pig":5,"minecraft:sheep":13,"minecraft:blaze":3,"minecraft:slime":12,"minecraft:llama":15,"minecraft:drowned":7,"minecraft:bat":1,"minecraft:hoglin":4,"minecraft:squid":35,"minecraft:wither_skeleton":23},"minecraft:used":{"minecraft:peony":10,"minecraft:dispenser":4,"minecraft:ladder":64,"minecraft:chest":76,"minecraft:warped_sign":5,"minecraft:quartz_stairs":162,"minecraft:soul_sand":5,"minecraft:weeping_vines":1,"minecraft:lava_bucket":13,"minecraft:netherite_shovel":5742,"minecraft:villager_spawn_egg":3,"minecraft:black_stained_glass_pane":534,"minecraft:grass_block":56,"minecraft:quartz_block":327,"minecraft:stone_brick_stairs":17,"minecraft:furnace":17,"minecraft:oak_sapling":1,"minecraft:potato":381,"minecraft:diorite":2,"minecraft:spruce_door":7,"minecraft:powered_rail":2,"minecraft:oak_leaves":87,"minecraft:sand":183,"minecraft:blast_furnace":8,"minecraft:gray_concrete":223,"minecraft:black_concrete_powder":34,"minecraft:stone_button":4,"minecraft:diamond_sword":1147,"minecraft:coal_block":1,"minecraft:smithing_table":3,"minecraft:oak_boat":6,"minecraft:diorite_stairs":1,"minecraft:iron_bars":102,"minecraft:enchanting_table":3,"minecraft:armor_stand":4,"minecraft:netherrack":162,"minecraft:torch":51,"minecraft:anvil":1,"minecraft:warped_wart_block":2,"minecraft:oak_fence_gate":3,"minecraft:shroomlight":69,"minecraft:iron_block":166,"minecraft:barrel":22,"minecraft:bamboo":31,"minecraft:tripwire_hook":3,"minecraft:glowstone":50,"minecraft:iron_trapdoor":1,"minecraft:water_bucket":59,"minecraft:warped_stem":26,"minecraft:sandstone_stairs":14,"minecraft:birch_planks":1,"minecraft:rail":4,"minecraft:oak_slab":29,"minecraft:tnt":3,"minecraft:crafting_table":13,"minecraft:white_bed":3,"minecraft:oak_log":331,"minecraft:diamond_pickaxe":4985,"minecraft:warped_trapdoor":2,"minecraft:diamond_shovel":1974,"minecraft:iron_pickaxe":750,"minecraft:spruce_trapdoor":17,"minecraft:blue_carpet":6,"minecraft:cobblestone":79,"minecraft:cooked_porkchop":63,"minecraft:sandstone_slab":2,"minecraft:stripped_oak_log":12,"minecraft:oak_sign":8,"minecraft:diamond_hoe":51,"minecraft:white_concrete_powder":1320,"minecraft:zombie_spawn_egg":5,"minecraft:bell":2,"minecraft:birch_pressure_plate":4,"minecraft:nether_bricks":8,"minecraft:obsidian":12,"minecraft:glass":211,"minecraft:cyan_terracotta":300,"minecraft:quartz_slab":489,"minecraft:lantern":140,"minecraft:gray_concrete_powder":352,"minecraft:crimson_roots":1,"minecraft:stone_bricks":31,"minecraft:item_frame":20,"minecraft:golden_sword":3,"minecraft:birch_trapdoor":31,"minecraft:repeater":6,"minecraft:red_carpet":3,"minecraft:scaffolding":230,"minecraft:wither_skeleton_skull":4,"minecraft:birch_leaves":1,"minecraft:stone_pickaxe":88,"minecraft:oak_planks":453,"minecraft:sandstone":68,"minecraft:sugar_cane":82,"minecraft:diamond_axe":1014,"minecraft:loom":2,"minecraft:yellow_concrete":277,"minecraft:stone_brick_wall":41,"minecraft:shears":172,"minecraft:redstone_torch":3,"minecraft:lever":4,"minecraft:black_concrete":3,"minecraft:light_gray_concrete":1584,"minecraft:cyan_bed":2,"minecraft:warped_slab":24,"minecraft:grindstone":1,"minecraft:andesite":10,"minecraft:smooth_stone_slab":152,"minecraft:chest_minecart":3,"minecraft:white_concrete":1244,"minecraft:bone_meal":7,"minecraft:oak_fence":10,"minecraft:netherite_sword":8,"minecraft:rose_bush":22,"minecraft:flint_and_steel":9,"minecraft:redstone":21,"minecraft:oak_door":47,"minecraft:dirt":1537,"minecraft:white_carpet":3,"minecraft:hopper":48,"minecraft:spruce_stairs":11,"minecraft:warped_door":5,"minecraft:spruce_fence":3,"minecraft:stone_brick_slab":95,"minecraft:bookshelf":32,"minecraft:yellow_concrete_powder":304,"minecraft:black_stained_glass":351,"minecraft:netherite_pickaxe":14616,"minecraft:cooked_beef":66,"minecraft:cobblestone_stairs":3,"minecraft:baked_potato":172,"minecraft:birch_boat":1,"minecraft:cut_sandstone":68,"minecraft:spruce_sign":1,"minecraft:beacon":1,"minecraft:warped_roots":3,"minecraft:light_gray_concrete_powder":1563,"minecraft:painting":45,"minecraft:warped_planks":30,"minecraft:gray_terracotta":1,"minecraft:flower_pot":5,"minecraft:apple":2,"minecraft:map":2,"minecraft:stone_axe":15,"minecraft:white_banner":1,"minecraft:bucket":75,"minecraft:yellow_bed":4,"minecraft:smooth_stone":103},"minecraft:picked_up":{"minecraft:birch_door":1,"minecraft:flower_pot":4,"minecraft:anvil":1,"minecraft:smithing_table":2,"minecraft:lead":13,"minecraft:diamond_sword":4,"minecraft:oak_stairs":1,"minecraft:wither_rose":1,"minecraft:golden_sword":2,"minecraft:string":12,"minecraft:soul_soil":1,"minecraft:shroomlight":76,"minecraft:diamond_leggings":1,"minecraft:gold_nugget":44,"minecraft:warped_slab":17,"minecraft:coal_block":1,"minecraft:melon_slice":24,"minecraft:warped_planks":6,"minecraft:warped_door":2,"minecraft:stone_sword":1,"minecraft:iron_block":3,"minecraft:blue_dye":2,"minecraft:carved_pumpkin":1,"minecraft:cyan_terracotta":98,"minecraft:bookshelf":16,"minecraft:blaze_rod":4,"minecraft:iron_bars":64,"minecraft:birch_log":57,"minecraft:magma_block":47,"minecraft:cooked_beef":15,"minecraft:flint":190,"minecraft:gray_concrete":193,"minecraft:lantern":139,"minecraft:light_gray_concrete_powder":523,"minecraft:gray_concrete_powder":352,"minecraft:gray_terracotta":1,"minecraft:diamond_helmet":1,"minecraft:glowstone_dust":340,"minecraft:chiseled_polished_blackstone":1,"minecraft:warped_wart_block":7,"minecraft:ink_sac":74,"minecraft:loom":2,"minecraft:barrel":5,"minecraft:dispenser":1,"minecraft:black_concrete_powder":2,"minecraft:lever":3,"minecraft:granite":219,"minecraft:crimson_roots":4,"minecraft:diamond_pickaxe":2,"minecraft:crafting_table":11,"minecraft:nether_wart":2,"minecraft:clay_ball":460,"minecraft:flint_and_steel":1,"minecraft:netherite_scrap":1,"minecraft:beef":82,"minecraft:poppy":33,"minecraft:minecart":3,"minecraft:quartz_stairs":60,"minecraft:chest":28,"minecraft:birch_sapling":4,"minecraft:sandstone":294,"minecraft:oak_door":48,"minecraft:spruce_fence":1,"minecraft:white_dye":16,"minecraft:carrot":87,"minecraft:redstone":57,"minecraft:netherite_pickaxe":2,"minecraft:diamond_chestplate":1,"minecraft:peony":13,"minecraft:shears":1,"minecraft:diamond_boots":1,"minecraft:hay_block":78,"minecraft:sandstone_stairs":4,"minecraft:gold_ingot":1,"minecraft:mutton":24,"minecraft:bone_block":18,"minecraft:white_wool":12,"minecraft:stripped_oak_log":22,"minecraft:birch_leaves":20,"minecraft:tripwire_hook":1,"minecraft:red_mushroom":1,"minecraft:filled_map":2,"minecraft:oak_log":795,"minecraft:ancient_debris":46,"minecraft:diorite_stairs":1,"minecraft:white_banner":2,"minecraft:stone_bricks":22,"minecraft:apple":3,"minecraft:warped_stem":152,"minecraft:stone_pickaxe":4,"minecraft:oak_fence_gate":1,"minecraft:iron_ore":482,"minecraft:sweet_berries":35,"minecraft:yellow_concrete":363,"minecraft:gravel":1598,"minecraft:crying_obsidian":1,"minecraft:diamond_shovel":3,"minecraft:slime_ball":10,"minecraft:stone_axe":2,"minecraft:diamond_axe":2,"minecraft:painting":41,"minecraft:warped_roots":3,"minecraft:hopper":11,"minecraft:wheat":1,"minecraft:iron_trapdoor":1,"minecraft:stone_brick_stairs":24,"minecraft:smooth_stone_slab":12,"minecraft:oak_sign":5,"minecraft:smooth_stone":107,"minecraft:bucket":9,"minecraft:white_tulip":74,"minecraft:rose_bush":37,"minecraft:redstone_torch":3,"minecraft:iron_pickaxe":1,"minecraft:furnace":17,"minecraft:stick":53,"minecraft:birch_trapdoor":8,"minecraft:torch":53,"minecraft:spruce_stairs":13,"minecraft:porkchop":21,"minecraft:diorite":137,"minecraft:quartz_block":303,"minecraft:cactus":4,"minecraft:rotten_flesh":55,"minecraft:obsidian":18,"minecraft:cobblestone":3901,"minecraft:enchanting_table":2,"minecraft:repeater":2,"minecraft:andesite":179,"minecraft:potato":269,"minecraft:warped_trapdoor":1,"minecraft:wither_skeleton_skull":5,"minecraft:lapis_lazuli":67,"minecraft:dirt":2608,"minecraft:glass":65,"minecraft:bone":76,"minecraft:bow":1,"minecraft:wheat_seeds":80,"minecraft:bell":4,"minecraft:grindstone":1,"minecraft:bamboo":245,"minecraft:oak_planks":112,"minecraft:cooked_porkchop":178,"minecraft:black_stained_glass_pane":4,"minecraft:sand":2981,"minecraft:cyan_bed":1,"minecraft:grass_block":1,"minecraft:chiseled_sandstone":1,"minecraft:light_gray_concrete":1485,"minecraft:diamond":426,"minecraft:black_concrete":27,"minecraft:cracked_polished_blackstone_bricks":23,"minecraft:emerald":48,"minecraft:white_concrete":1405,"minecraft:bone_meal":23,"minecraft:spruce_sign":2,"minecraft:oak_sapling":39,"minecraft:netherrack":4869,"minecraft:oak_leaves":146,"minecraft:nether_star":1,"minecraft:ladder":43,"minecraft:stone_brick_wall":16,"minecraft:gold_block":15,"minecraft:iron_axe":1,"minecraft:item_frame":7,"minecraft:quartz_slab":181,"minecraft:blackstone":144,"minecraft:oak_boat":7,"minecraft:light_gray_wool":1,"minecraft:sugar_cane":180,"minecraft:spruce_trapdoor":19,"minecraft:polished_blackstone_bricks":51,"minecraft:stone_button":1,"minecraft:weeping_vines":2,"minecraft:arrow":44,"minecraft:nether_bricks":21,"minecraft:pink_tulip":1,"minecraft:cut_sandstone":25,"minecraft:leather":63,"minecraft:birch_planks":1,"minecraft:yellow_bed":3,"minecraft:nether_wart_block":5,"minecraft:gunpowder":3,"minecraft:cobblestone_stairs":3,"minecraft:iron_ingot":17,"minecraft:soul_sand":34,"minecraft:oak_slab":40,"minecraft:scaffolding":176,"minecraft:warped_fungus":1,"minecraft:birch_boat":1,"minecraft:stone_brick_slab":47,"minecraft:quartz":3824,"minecraft:dandelion":38,"minecraft:blast_furnace":4,"minecraft:white_bed":3,"minecraft:gold_ore":10,"minecraft:spruce_door":6,"minecraft:spider_eye":4,"minecraft:white_concrete_powder":233,"minecraft:coal":1636},"minecraft:dropped":{"minecraft:diamond":38,"minecraft:dirt":520,"minecraft:gold_nugget":42,"minecraft:sand":7,"minecraft:bone":16,"minecraft:diamond_block":3,"minecraft:iron_nugget":7,"minecraft:wheat":1,"minecraft:grindstone":1,"minecraft:rotten_flesh":20,"minecraft:oak_planks":2,"minecraft:glowstone_dust":3,"minecraft:warped_planks":1,"minecraft:quartz_block":223,"minecraft:ladder":4,"minecraft:white_dye":15,"minecraft:beef":2,"minecraft:warped_wart_block":2,"minecraft:stone_brick_stairs":23,"minecraft:netherite_pickaxe":3,"minecraft:wheat_seeds":17,"minecraft:cobblestone":560,"minecraft:granite":10,"minecraft:spruce_door":2,"minecraft:coal":13,"minecraft:ink_sac":2,"minecraft:wooden_axe":1,"minecraft:string":3,"minecraft:stone_brick_slab":3,"minecraft:pink_tulip":1,"minecraft:light_gray_concrete":5,"minecraft:spruce_fence":1,"minecraft:diamond_sword":3,"minecraft:potato":65,"minecraft:peony":2,"minecraft:spruce_trapdoor":8,"minecraft:diamond_pickaxe":1,"minecraft:carved_pumpkin":1,"minecraft:spider_eye":4,"minecraft:stone_bricks":139,"minecraft:sandstone":2,"minecraft:bow":1,"minecraft:bell":1,"minecraft:magma_block":43,"minecraft:quartz_slab":47,"minecraft:terracotta":8,"minecraft:diamond_axe":1,"minecraft:oak_log":17,"minecraft:sandstone_slab":16,"minecraft:lantern":71,"minecraft:flint":113,"minecraft:cyan_terracotta":4,"minecraft:cracked_polished_blackstone_bricks":23,"minecraft:netherite_scrap":1,"minecraft:crimson_roots":3,"minecraft:cut_sandstone":6,"minecraft:gravel":111,"minecraft:chiseled_polished_blackstone":1,"minecraft:blackstone":1,"minecraft:diamond_shovel":2,"minecraft:poppy":3941,"minecraft:gunpowder":2,"minecraft:stone_brick_wall":1,"minecraft:arrow":24,"minecraft:white_concrete_powder":73,"minecraft:quartz":1091,"minecraft:oak_leaves":13,"minecraft:netherrack":3710,"minecraft:bread":39,"minecraft:oak_slab":2,"minecraft:yellow_concrete":56,"minecraft:lead":6,"minecraft:spruce_stairs":9,"minecraft:grass_block":1,"minecraft:stick":7,"minecraft:diorite":60,"minecraft:torch":64,"minecraft:nether_wart_block":2,"minecraft:iron_axe":1,"minecraft:bucket":9,"minecraft:dandelion":1,"minecraft:redstone":7,"minecraft:wither_skeleton_skull":1,"minecraft:stripped_oak_log":3,"minecraft:flint_and_steel":1,"minecraft:filled_map":1,"minecraft:gray_terracotta":64,"minecraft:andesite":19,"minecraft:quartz_stairs":6,"minecraft:oak_boat":3,"minecraft:oak_sapling":8},"minecraft:mined":{"minecraft:white_bed":9,"minecraft:obsidian":18,"minecraft:granite":277,"minecraft:chiseled_polished_blackstone":1,"minecraft:stone_brick_wall":2,"minecraft:coal_block":1,"minecraft:diorite_stairs":1,"minecraft:hopper":11,"minecraft:oak_wall_sign":1,"minecraft:nether_wart":2,"minecraft:polished_blackstone_bricks":41,"minecraft:weeping_vines_plant":1,"minecraft:tall_seagrass":3,"minecraft:magma_block":64,"minecraft:fire":3,"minecraft:barrel":3,"minecraft:enchanting_table":2,"minecraft:oak_sign":1,"minecraft:oak_stairs":1,"minecraft:quartz_slab":156,"minecraft:light_gray_concrete":1518,"minecraft:pink_tulip":2,"minecraft:iron_block":3,"minecraft:cut_sandstone":25,"minecraft:kelp_plant":1,"minecraft:crimson_nylium":26,"minecraft:torch":25,"minecraft:blast_furnace":4,"minecraft:melon":5,"minecraft:spruce_wall_sign":1,"minecraft:glass":103,"minecraft:cyan_bed":1,"minecraft:sugar_cane":102,"minecraft:spruce_sign":1,"minecraft:repeater":2,"minecraft:black_concrete_powder":2,"minecraft:wheat":15,"minecraft:stone_brick_stairs":8,"minecraft:grass":137,"minecraft:oak_fence_gate":1,"minecraft:loom":2,"minecraft:warped_door":2,"minecraft:nether_bricks":23,"minecraft:crimson_roots":5,"minecraft:redstone_wire":5,"minecraft:black_stained_glass_pane":61,"minecraft:redstone_ore":11,"minecraft:andesite":235,"minecraft:warped_wall_sign":1,"minecraft:potatoes":38,"minecraft:rail":4,"minecraft:warped_stem":138,"minecraft:warped_trapdoor":1,"minecraft:bamboo_sapling":13,"minecraft:bamboo":3,"minecraft:bone_block":18,"minecraft:smithing_table":2,"minecraft:oak_slab":39,"minecraft:gray_concrete":193,"minecraft:soul_sand":43,"minecraft:stone_brick_slab":21,"minecraft:dandelion":39,"minecraft:light_gray_concrete_powder":3,"minecraft:emerald_ore":25,"minecraft:warped_roots":3,"minecraft:tall_grass":31,"minecraft:diorite":153,"minecraft:warped_wart_block":7,"minecraft:black_stained_glass":15,"minecraft:birch_leaves":35,"minecraft:sunflower":2,"minecraft:gravel":1919,"minecraft:stone_bricks":12,"minecraft:gold_ore":10,"minecraft:iron_trapdoor":1,"minecraft:infested_stone":7,"minecraft:oak_sapling":1,"minecraft:cobblestone_stairs":3,"minecraft:potted_cactus":4,"minecraft:spruce_trapdoor":15,"minecraft:grass_block":1721,"minecraft:cracked_polished_blackstone_bricks":21,"minecraft:white_concrete":1441,"minecraft:soul_soil":1,"minecraft:sandstone_stairs":4,"minecraft:smooth_stone":87,"minecraft:glowstone":101,"minecraft:iron_ore":357,"minecraft:anvil":1,"minecraft:iron_bars":39,"minecraft:gray_terracotta":1,"minecraft:quartz_block":141,"minecraft:cyan_terracotta":100,"minecraft:blackstone":159,"minecraft:clay":116,"minecraft:poppy":8,"minecraft:chest":27,"minecraft:nether_quartz_ore":2384,"minecraft:wither_skeleton_wall_skull":1,"minecraft:cobblestone":23,"minecraft:grindstone":1,"minecraft:oak_planks":54,"minecraft:wall_torch":18,"minecraft:warped_nylium":5,"minecraft:powered_rail":2,"minecraft:warped_planks":5,"minecraft:nether_wart_block":5,"minecraft:birch_log":21,"minecraft:birch_trapdoor":8,"minecraft:tnt":1,"minecraft:smooth_stone_slab":11,"minecraft:oak_log":101,"minecraft:sand":3163,"minecraft:dirt":1088,"minecraft:tripwire_hook":1,"minecraft:wither_skeleton_skull":1,"minecraft:dispenser":1,"minecraft:netherrack":7085,"minecraft:ancient_debris":44,"minecraft:oak_leaves":296,"minecraft:nether_gold_ore":15,"minecraft:diamond_ore":224,"minecraft:crying_obsidian":1,"minecraft:quartz_stairs":60,"minecraft:dark_oak_leaves":1,"minecraft:oak_door":2,"minecraft:lever":3,"minecraft:ladder":29,"minecraft:weeping_vines":1,"minecraft:spruce_leaves":2,"minecraft:sandstone":366,"minecraft:large_fern":2,"minecraft:hay_block":78,"minecraft:furnace":14,"minecraft:carrots":7,"minecraft:chiseled_sandstone":1,"minecraft:black_concrete":27,"minecraft:peony":11,"minecraft:gold_block":15,"minecraft:bell":3,"minecraft:bookshelf":16,"minecraft:shroomlight":68,"minecraft:lantern":42,"minecraft:stripped_oak_log":30,"minecraft:packed_ice":15,"minecraft:stone":3528,"minecraft:white_tulip":73,"minecraft:redstone_wall_torch":3,"minecraft:scaffolding":64,"minecraft:spruce_door":2,"minecraft:crafting_table":9,"minecraft:rose_bush":37,"minecraft:lapis_ore":8,"minecraft:spruce_stairs":4,"minecraft:birch_planks":1,"minecraft:sweet_berry_bush":13,"minecraft:yellow_bed":3,"minecraft:grass_path":3,"minecraft:coal_ore":622,"minecraft:yellow_concrete":363,"minecraft:warped_slab":18},"minecraft:crafted":{"minecraft:black_dye":70,"minecraft:light_gray_concrete_powder":1192,"minecraft:smooth_stone":41,"minecraft:oak_sign":12,"minecraft:cut_sandstone":132,"minecraft:birch_boat":1,"minecraft:lever":1,"minecraft:diamond_shovel":2,"minecraft:bookshelf":16,"minecraft:iron_bars":112,"minecraft:quartz_block":626,"minecraft:glass":256,"minecraft:diamond_helmet":2,"minecraft:repeater":4,"minecraft:diamond_leggings":2,"minecraft:beacon":1,"minecraft:melon_seeds":3,"minecraft:flower_pot":1,"minecraft:diamond_axe":3,"minecraft:chest_minecart":4,"minecraft:spruce_door":3,"minecraft:smithing_table":1,"minecraft:painting":4,"minecraft:stone_brick_stairs":16,"minecraft:iron_pickaxe":2,"minecraft:iron_block":934,"minecraft:gold_ingot":45,"minecraft:light_gray_dye":74,"minecraft:netherite_ingot":11,"minecraft:yellow_concrete_powder":304,"minecraft:smooth_stone_slab":234,"minecraft:iron_nugget":486,"minecraft:diamond_hoe":1,"minecraft:bone_meal":325,"minecraft:spruce_fence":3,"minecraft:white_carpet":3,"minecraft:warped_trapdoor":2,"minecraft:terracotta":104,"minecraft:lantern":48,"minecraft:diamond":36,"minecraft:spruce_stairs":16,"minecraft:black_concrete_powder":32,"minecraft:ladder":27,"minecraft:stone_pickaxe":2,"minecraft:diamond_boots":2,"minecraft:quartz_slab":384,"minecraft:wheat":126,"minecraft:coal_block":115,"minecraft:enchanting_table":1,"minecraft:sandstone_slab":18,"minecraft:red_carpet":3,"minecraft:glowstone":68,"minecraft:oak_fence_gate":2,"minecraft:warped_sign":12,"minecraft:birch_trapdoor":24,"minecraft:black_stained_glass_pane":576,"minecraft:iron_leggings":1,"minecraft:armor_stand":10,"minecraft:blue_carpet":6,"minecraft:brick":44,"minecraft:oak_planks":1352,"minecraft:barrel":19,"minecraft:stone":95,"minecraft:warped_planks":504,"minecraft:green_dye":4,"minecraft:hopper":25,"minecraft:stone_brick_slab":94,"minecraft:bow":3,"minecraft:iron_boots":1,"minecraft:cyan_terracotta":32,"minecraft:chest":76,"minecraft:rail":16,"minecraft:stone_bricks":284,"minecraft:oak_fence":48,"minecraft:golden_boots":1,"minecraft:quartz_stairs":108,"minecraft:oak_slab":72,"minecraft:item_frame":11,"minecraft:crafting_table":19,"minecraft:spruce_planks":112,"minecraft:iron_helmet":1,"minecraft:birch_pressure_plate":4,"minecraft:red_wool":2,"minecraft:birch_planks":192,"minecraft:warped_door":6,"minecraft:dispenser":3,"minecraft:spruce_trapdoor":10,"minecraft:book":50,"minecraft:iron_chestplate":1,"minecraft:paper":267,"minecraft:diamond_pickaxe":6,"minecraft:yellow_dye":34,"minecraft:gray_terracotta":64,"minecraft:stick":456,"minecraft:warped_slab":54,"minecraft:iron_ingot":306,"minecraft:redstone_torch":11,"minecraft:shears":2,"minecraft:sandstone_stairs":40,"minecraft:oak_door":3,"minecraft:stone_brick_wall":36,"minecraft:furnace":11,"minecraft:stone_button":5,"minecraft:blast_furnace":4,"minecraft:gray_dye":8,"minecraft:diamond_block":38,"minecraft:glass_pane":48,"minecraft:flint_and_steel":1,"minecraft:white_concrete_powder":1232,"minecraft:netherite_scrap":20,"minecraft:minecart":1,"minecraft:cooked_beef":64,"minecraft:red_dye":2,"minecraft:diamond_sword":3,"minecraft:cyan_dye":8,"minecraft:iron_trapdoor":1,"minecraft:powered_rail":6,"minecraft:bucket":6,"minecraft:stone_axe":1,"minecraft:air":0,"minecraft:bread":39,"minecraft:black_stained_glass":600,"minecraft:blue_dye":10,"minecraft:oak_boat":3,"minecraft:white_dye":179,"minecraft:blue_wool":4,"minecraft:anvil":1,"minecraft:torch":132,"minecraft:clay":104,"minecraft:diamond_chestplate":2},"minecraft:custom":{"minecraft:interact_with_crafting_table":260,"minecraft:open_barrel":13,"minecraft:bell_ring":14,"minecraft:leave_game":36,"minecraft:time_since_death":35116,"minecraft:deaths":48,"minecraft:jump":23434,"minecraft:enchant_item":20,"minecraft:interact_with_furnace":220,"minecraft:damage_dealt":54372,"minecraft:interact_with_smoker":2,"minecraft:inspect_dispenser":11,"minecraft:horse_one_cm":17663,"minecraft:interact_with_smithing_table":11,"minecraft:interact_with_anvil":10,"minecraft:inspect_hopper":108,"minecraft:sneak_time":96157,"minecraft:interact_with_blast_furnace":59,"minecraft:interact_with_stonecutter":1,"minecraft:time_since_rest":35171,"minecraft:swim_one_cm":228680,"minecraft:fly_one_cm":6906990,"minecraft:open_chest":1652,"minecraft:fall_one_cm":597616,"minecraft:sprint_one_cm":3549665,"minecraft:drop":416,"minecraft:talked_to_villager":31,"minecraft:walk_on_water_one_cm":610440,"minecraft:play_one_minute":1800289,"minecraft:interact_with_loom":6,"minecraft:interact_with_beacon":5,"minecraft:player_kills":7,"minecraft:crouch_one_cm":337308,"minecraft:mob_kills":303,"minecraft:climb_one_cm":137097,"minecraft:walk_one_cm":6009824,"minecraft:walk_under_water_one_cm":309043,"minecraft:boat_one_cm":653484,"minecraft:raid_trigger":1,"minecraft:pot_flower":5,"minecraft:interact_with_grindstone":1,"minecraft:damage_taken":31906}},"DataVersion":2586}