{"stats":{"minecraft:dropped":{"minecraft:dark_oak_log":4,"minecraft:dark_oak_fence":1,"minecraft:sand":33,"minecraft:bone":7,"minecraft:gravel":4,"minecraft:white_tulip":1,"minecraft:rotten_flesh":15,"minecraft:oak_planks":1,"minecraft:white_concrete_powder":64,"minecraft:light_gray_concrete_powder":106,"minecraft:bread":5,"minecraft:oak_fence":20,"minecraft:cobblestone":1,"minecraft:coal":28,"minecraft:torch":16,"minecraft:wooden_axe":1,"minecraft:white_concrete":43,"minecraft:iron_leggings":1,"minecraft:iron_axe":2,"minecraft:iron_shovel":1,"minecraft:string":1,"minecraft:bucket":1,"minecraft:beetroot_soup":2,"minecraft:iron_boots":1,"minecraft:shears":1,"minecraft:diamond_sword":1,"minecraft:spruce_planks":3,"minecraft:diamond_pickaxe":3,"minecraft:iron_chestplate":1,"minecraft:light_gray_dye":74},"minecraft:crafted":{"minecraft:light_gray_concrete_powder":120,"minecraft:yellow_wool":2,"minecraft:oak_planks":544,"minecraft:stone":812,"minecraft:iron_bars":16,"minecraft:quartz_block":204,"minecraft:glass":200,"minecraft:stone_brick_slab":330,"minecraft:iron_boots":1,"minecraft:melon_seeds":7,"minecraft:chest":48,"minecraft:birch_door":3,"minecraft:stone_bricks":812,"minecraft:quartz_stairs":84,"minecraft:oak_slab":330,"minecraft:cooked_porkchop":3,"minecraft:crafting_table":1,"minecraft:wooden_pickaxe":1,"minecraft:red_wool":2,"minecraft:hay_block":1,"minecraft:birch_planks":140,"minecraft:pumpkin_seeds":12,"minecraft:stone_brick_stairs":72,"minecraft:iron_chestplate":1,"minecraft:diamond_pickaxe":6,"minecraft:charcoal":8,"minecraft:yellow_dye":2,"minecraft:shield":1,"minecraft:stick":60,"minecraft:light_blue_dye":2,"minecraft:iron_ingot":284,"minecraft:iron_pickaxe":8,"minecraft:iron_block":3,"minecraft:gold_ingot":12,"minecraft:light_gray_dye":89,"minecraft:shears":1,"minecraft:stone_shovel":4,"minecraft:stone_brick_wall":162,"minecraft:iron_nugget":180,"minecraft:furnace":12,"minecraft:bone_meal":90,"minecraft:oak_trapdoor":16,"minecraft:glass_pane":160,"minecraft:lantern":22,"minecraft:white_concrete_powder":624,"minecraft:iron_axe":4,"minecraft:ladder":15,"minecraft:iron_hoe":1,"minecraft:stone_pickaxe":2,"minecraft:quartz_slab":102,"minecraft:red_dye":4,"minecraft:diamond_sword":1,"minecraft:yellow_carpet":3,"minecraft:light_blue_wool":2,"minecraft:bucket":1,"minecraft:red_carpet":3,"minecraft:stone_axe":2,"minecraft:white_stained_glass":32,"minecraft:bread":36,"minecraft:air":0,"minecraft:light_blue_carpet":3,"minecraft:white_dye":82,"minecraft:wooden_axe":1,"minecraft:black_carpet":3,"minecraft:iron_shovel":9,"minecraft:iron_leggings":1,"minecraft:anvil":1,"minecraft:torch":196},"minecraft:mined":{"minecraft:dark_oak_planks":1,"minecraft:blue_carpet":3,"minecraft:spruce_planks":3,"minecraft:brewing_stand":2,"minecraft:granite":125,"minecraft:grass_block":1245,"minecraft:stone_brick_wall":7,"minecraft:white_concrete":43,"minecraft:crimson_fungus":3,"minecraft:iron_ore":288,"minecraft:pumpkin":7,"minecraft:oak_sign":1,"minecraft:quartz_slab":1,"minecraft:purple_carpet":3,"minecraft:blue_orchid":4,"minecraft:quartz_block":4,"minecraft:kelp_plant":1,"minecraft:crimson_nylium":3,"minecraft:torch":29,"minecraft:poppy":2,"minecraft:melon":41,"minecraft:chest":24,"minecraft:glass":3,"minecraft:nether_quartz_ore":564,"minecraft:cobblestone":10,"minecraft:sugar_cane":349,"minecraft:oak_planks":6,"minecraft:wall_torch":27,"minecraft:birch_sapling":1,"minecraft:nether_wart_block":6,"minecraft:birch_log":37,"minecraft:wheat":119,"minecraft:lilac":5,"minecraft:stone_brick_stairs":10,"minecraft:grass":60,"minecraft:oak_log":450,"minecraft:sand":722,"minecraft:dirt":453,"minecraft:stonecutter":2,"minecraft:netherrack":259,"minecraft:oak_leaves":192,"minecraft:nether_gold_ore":1,"minecraft:diamond_ore":25,"minecraft:red_carpet":3,"minecraft:quartz_stairs":5,"minecraft:oak_door":1,"minecraft:nether_bricks":2,"minecraft:crimson_stem":3,"minecraft:hay_block":63,"minecraft:redstone_ore":29,"minecraft:oak_trapdoor":1,"minecraft:furnace":6,"minecraft:carrots":39,"minecraft:andesite":122,"minecraft:bookshelf":13,"minecraft:potatoes":123,"minecraft:shroomlight":12,"minecraft:lantern":85,"minecraft:packed_ice":6,"minecraft:stone":2230,"minecraft:white_tulip":90,"minecraft:oak_slab":16,"minecraft:stone_brick_slab":31,"minecraft:dandelion":4,"minecraft:oak_fence":9,"minecraft:crafting_table":2,"minecraft:rose_bush":2,"minecraft:lapis_ore":23,"minecraft:diorite":155,"minecraft:blue_bed":3,"minecraft:white_carpet":1,"minecraft:birch_leaves":6,"minecraft:grass_path":2,"minecraft:coal_ore":758,"minecraft:gravel":420,"minecraft:stone_bricks":3,"minecraft:gold_ore":13},"minecraft:custom":{"minecraft:animals_bred":14,"minecraft:interact_with_crafting_table":214,"minecraft:open_barrel":5,"minecraft:bell_ring":4,"minecraft:leave_game":36,"minecraft:time_since_death":16694,"minecraft:sprint_one_cm":2463399,"minecraft:damage_blocked_by_shield":130,"minecraft:drop":97,"minecraft:talked_to_villager":3,"minecraft:deaths":2,"minecraft:jump":7925,"minecraft:walk_on_water_one_cm":162864,"minecraft:enchant_item":7,"minecraft:interact_with_furnace":314,"minecraft:play_one_minute":904999,"minecraft:damage_dealt":20058,"minecraft:crouch_one_cm":160284,"minecraft:horse_one_cm":39359,"minecraft:mob_kills":126,"minecraft:climb_one_cm":65968,"minecraft:walk_one_cm":2490761,"minecraft:sneak_time":52388,"minecraft:walk_under_water_one_cm":69933,"minecraft:interact_with_stonecutter":1,"minecraft:time_since_rest":16741,"minecraft:damage_taken":6933,"minecraft:swim_one_cm":184627,"minecraft:fly_one_cm":1832371,"minecraft:open_chest":1018,"minecraft:fall_one_cm":126119},"minecraft:picked_up":{"minecraft:birch_door":4,"minecraft:wheat":118,"minecraft:lead":27,"minecraft:stone_brick_stairs":10,"minecraft:brewing_stand":2,"minecraft:string":5,"minecraft:beetroot_soup":1,"minecraft:shroomlight":12,"minecraft:oak_sign":1,"minecraft:gold_nugget":5,"minecraft:spruce_planks":3,"minecraft:white_tulip":90,"minecraft:rose_bush":2,"minecraft:melon_slice":212,"minecraft:furnace":6,"minecraft:stick":130,"minecraft:oak_fence":128,"minecraft:torch":70,"minecraft:spruce_stairs":1,"minecraft:porkchop":3,"minecraft:diorite":155,"minecraft:quartz_block":4,"minecraft:rotten_flesh":29,"minecraft:cobblestone":2233,"minecraft:birch_log":38,"minecraft:lilac":5,"minecraft:andesite":122,"minecraft:potato":396,"minecraft:flint":43,"minecraft:stripped_spruce_wood":74,"minecraft:lapis_lazuli":209,"minecraft:dirt":1698,"minecraft:lantern":96,"minecraft:purple_carpet":3,"minecraft:bone":35,"minecraft:glass":1,"minecraft:stonecutter":2,"minecraft:bow":2,"minecraft:wheat_seeds":322,"minecraft:oak_planks":22,"minecraft:sand":722,"minecraft:ink_sac":61,"minecraft:dark_oak_log":4,"minecraft:diamond":34,"minecraft:granite":125,"minecraft:white_concrete":43,"minecraft:oak_sapling":240,"minecraft:netherrack":229,"minecraft:dark_oak_fence":1,"minecraft:diamond_pickaxe":1,"minecraft:crafting_table":2,"minecraft:ladder":1,"minecraft:stone_brick_wall":7,"minecraft:oak_trapdoor":1,"minecraft:iron_axe":1,"minecraft:white_carpet":1,"minecraft:quartz_slab":1,"minecraft:blue_orchid":4,"minecraft:poppy":4,"minecraft:light_gray_wool":2,"minecraft:quartz_stairs":5,"minecraft:sugar_cane":405,"minecraft:chest":24,"minecraft:birch_sapling":13,"minecraft:egg":1,"minecraft:oak_door":1,"minecraft:spruce_fence":11,"minecraft:carrot":146,"minecraft:redstone":124,"minecraft:blue_carpet":3,"minecraft:dark_oak_planks":1,"minecraft:arrow":21,"minecraft:nether_bricks":2,"minecraft:hay_block":88,"minecraft:mutton":29,"minecraft:white_wool":18,"minecraft:stripped_oak_log":21,"minecraft:crimson_stem":3,"minecraft:crimson_fungus":3,"minecraft:oak_log":505,"minecraft:lily_pad":2,"minecraft:nether_wart_block":6,"minecraft:gunpowder":4,"minecraft:blue_bed":3,"minecraft:red_carpet":3,"minecraft:apple":18,"minecraft:stone_bricks":3,"minecraft:kelp":6,"minecraft:iron_ore":287,"minecraft:book":39,"minecraft:oak_slab":17,"minecraft:pumpkin":7,"minecraft:stone_brick_slab":32,"minecraft:quartz":823,"minecraft:dandelion":7,"minecraft:gravel":377,"minecraft:gold_ore":13,"minecraft:spider_eye":3,"minecraft:white_concrete_powder":64,"minecraft:gray_wool":1,"minecraft:black_wool":2,"minecraft:coal":1188},"minecraft:broken":{"minecraft:iron_shovel":8,"minecraft:golden_shovel":1,"minecraft:stone_pickaxe":2,"minecraft:stone_axe":2,"minecraft:stone_shovel":4,"minecraft:leather_helmet":1,"minecraft:wooden_pickaxe":1,"minecraft:iron_axe":2,"minecraft:iron_pickaxe":8},"minecraft:killed":{"minecraft:witch":1,"minecraft:spider":6,"minecraft:skeleton":26,"minecraft:pig":1,"minecraft:creeper":3,"minecraft:sheep":23,"minecraft:zombie":22,"minecraft:horse":1,"minecraft:drowned":5,"minecraft:bat":1,"minecraft:wandering_trader":3,"minecraft:squid":32,"minecraft:wither_skeleton":1},"minecraft:used":{"minecraft:iron_shovel":2180,"minecraft:poppy":1,"minecraft:ladder":15,"minecraft:oak_sign":1,"minecraft:white_concrete_powder":64,"minecraft:chest":72,"minecraft:shield":4,"minecraft:quartz_stairs":87,"minecraft:rotten_flesh":4,"minecraft:carrot":91,"minecraft:snowball":17,"minecraft:glass":93,"minecraft:quartz_slab":103,"minecraft:lantern":32,"minecraft:birch_sapling":1,"minecraft:quartz_block":4,"minecraft:stone_brick_stairs":82,"minecraft:stone_bricks":378,"minecraft:bow":4,"minecraft:hay_block":3,"minecraft:sweet_berries":6,"minecraft:furnace":18,"minecraft:oak_sapling":84,"minecraft:egg":1,"minecraft:potato":172,"minecraft:diorite":60,"minecraft:stone_pickaxe":262,"minecraft:oak_planks":6,"minecraft:wooden_pickaxe":59,"minecraft:sugar_cane":56,"minecraft:sand":144,"minecraft:stone_brick_wall":169,"minecraft:pumpkin_seeds":10,"minecraft:bread":69,"minecraft:diamond_sword":202,"minecraft:white_stained_glass":28,"minecraft:andesite":8,"minecraft:bone_meal":4,"minecraft:oak_fence":116,"minecraft:oak_trapdoor":17,"minecraft:iron_bars":16,"minecraft:stone_shovel":528,"minecraft:netherrack":3,"minecraft:oak_door":1,"minecraft:torch":212,"minecraft:dirt":1049,"minecraft:anvil":1,"minecraft:golden_shovel":32,"minecraft:granite":26,"minecraft:shroomlight":9,"minecraft:birch_door":6,"minecraft:iron_hoe":165,"minecraft:stone_brick_slab":337,"minecraft:iron_axe":597,"minecraft:melon_seeds":10,"minecraft:crimson_stem":3,"minecraft:wheat_seeds":166,"minecraft:water_bucket":10,"minecraft:iron_ore":3,"minecraft:gold_ore":1,"minecraft:oak_slab":375,"minecraft:crafting_table":3,"minecraft:light_gray_concrete_powder":14,"minecraft:oak_log":240,"minecraft:diamond_pickaxe":2529,"minecraft:apple":9,"minecraft:iron_pickaxe":2001,"minecraft:stone_axe":218,"minecraft:crimson_fungus":3,"minecraft:cobblestone":269,"minecraft:cooked_porkchop":67,"minecraft:bucket":10,"minecraft:glass_pane":141,"minecraft:stripped_oak_log":21}},"DataVersion":2586}